ryzenai_onnx_utils/__init__.py
ryzenai_onnx_utils/lexer.py
ryzenai_onnx_utils/matcher.py
ryzenai_onnx_utils/partitioner.py
ryzenai_onnx_utils/pattern.py
ryzenai_onnx_utils/pattern_generator.py
ryzenai_onnx_utils/postprocess.py
ryzenai_onnx_utils/preprocess.py
ryzenai_onnx_utils/utils.py
ryzenai_onnx_utils/vaiml.py
ryzenai_onnx_utils/data/partition_strategies/cleanup.yaml
ryzenai_onnx_utils/data/partition_strategies/hybrid_llm.yaml
ryzenai_onnx_utils/data/partition_strategies/hybrid_llm_experimental.yaml
ryzenai_onnx_utils/data/partition_strategies/hybrid_llm_fusion.yaml
ryzenai_onnx_utils/data/partition_strategies/hybrid_llm_npu.yaml
ryzenai_onnx_utils/data/vaiml/llm-dummy.onnx
ryzenai_onnx_utils/data/vaiml/oga_2x4x4_overlay.json
ryzenai_onnx_utils/model_postprocessing/__init__.py
ryzenai_onnx_utils/model_postprocessing/combine_llm.py
ryzenai_onnx_utils/passes/__init__.py
ryzenai_onnx_utils/passes/fastgelu_to_gelu.py
ryzenai_onnx_utils/passes/flatmha_external_bufs.py
ryzenai_onnx_utils/passes/hybrid_llm_add_cast_attributes.py
ryzenai_onnx_utils/passes/hybrid_llm_add_empty_cast_attributes.py
ryzenai_onnx_utils/passes/hybrid_llm_flatmlp.py
ryzenai_onnx_utils/passes/hybrid_llm_flatrmsadd.py
ryzenai_onnx_utils/passes/hybrid_llm_gqa.py
ryzenai_onnx_utils/passes/hybrid_llm_gqa_flatmha.py
ryzenai_onnx_utils/passes/hybrid_llm_gqa_rotary_dim.py
ryzenai_onnx_utils/passes/hybrid_llm_gqo.py
ryzenai_onnx_utils/passes/hybrid_llm_jit.py
ryzenai_onnx_utils/passes/hybrid_llm_kv_cache_to_bf16.py
ryzenai_onnx_utils/passes/hybrid_llm_matmulnbits.py
ryzenai_onnx_utils/passes/hybrid_llm_mlp.py
ryzenai_onnx_utils/passes/hybrid_llm_prune_logits.py
ryzenai_onnx_utils/passes/hybrid_llm_simplify_casts.py
ryzenai_onnx_utils/passes/hybrid_llm_ssmlp.py
ryzenai_onnx_utils/passes/normalize_matmulnbits.py
ryzenai_onnx_utils/passes/remove_dangling_nodes.py
ryzenai_onnx_utils/passes/remove_parallel_casts.py
ryzenai_onnx_utils/passes/remove_unused_inputs.py
ryzenai_onnx_utils/passes/simplify_casts.py
ryzenai_onnx_utils-1.5.0.dist-info/licenses/LICENSE.txt
ryzenai_onnx_utils-1.5.0.dist-info/METADATA
ryzenai_onnx_utils-1.5.0.dist-info/WHEEL
ryzenai_onnx_utils-1.5.0.dist-info/entry_points.txt
ryzenai_onnx_utils-1.5.0.dist-info/RECORD
