Metadata-Version: 2.4
Name: ryzenai_onnx_utils
Version: 1.5.0
Summary: onnx utils
Requires-Python: >=3.9
Requires-Dist: ml-dtypes
Requires-Dist: numpy
Requires-Dist: onnx
Requires-Dist: onnx-tool
Requires-Dist: pyyaml
Requires-Dist: rich
Requires-Dist: sympy
Provides-Extra: dev
Requires-Dist: pre-commit; extra == 'dev'
Requires-Dist: pytest; extra == 'dev'
Provides-Extra: docs
Requires-Dist: sphinx; extra == 'docs'
Requires-Dist: sphinx-argparse; extra == 'docs'
Requires-Dist: sphinx-copybutton; extra == 'docs'
Requires-Dist: sphinx-favicon; extra == 'docs'
Requires-Dist: sphinx-issues; extra == 'docs'
Requires-Dist: sphinx-rtd-theme; extra == 'docs'
Requires-Dist: sphinx-tabs; extra == 'docs'
Requires-Dist: sphinx-tippy; extra == 'docs'
Requires-Dist: sphinx-toolbox; extra == 'docs'
Requires-Dist: sphinxcontrib-jquery; extra == 'docs'
Requires-Dist: sphinxemoji; extra == 'docs'
License-File: LICENSE.txt
